langrinder/__init__.py
langrinder/exceptions.py
langrinder/main.py
langrinder/node.py
langrinder/rules.py
langrinder/types.py
langrinder/cli/__init__.py
langrinder/cli/main.py
langrinder/compiler/__init__.py
langrinder/compiler/abc.py
langrinder/compiler/json_compiler.py
langrinder/integrations/__init__.py
langrinder/integrations/telegrinder/__init__.py
langrinder/integrations/telegrinder/config.py
langrinder/integrations/telegrinder/rules.py
langrinder/integrations/telegrinder/sources.py
langrinder/integrations/telegrinder/translator.py
langrinder/manager/__init__.py
langrinder/manager/manager.py
langrinder/parser/__init__.py
langrinder/parser/abc.py
langrinder/parser/common.py
langrinder/tools/__init__.py
langrinder/tools/html.py
langrinder/tools/imports.py
langrinder/tools/pluralizer.py
langrinder-3.2.1.dist-info/licenses/LICENSE
langrinder-3.2.1.dist-info/METADATA
langrinder-3.2.1.dist-info/WHEEL
langrinder-3.2.1.dist-info/entry_points.txt
langrinder-3.2.1.dist-info/top_level.txt
langrinder-3.2.1.dist-info/RECORD
