Metadata-Version: 2.4
Name: langrinder
Version: 3.2.1
Summary: Flexible internationalization engine based on Mako templates
Author-email: ventuero <amerfoe@gmail.com>
Requires-Python: <4.0,>=3.12
License-File: LICENSE
Requires-Dist: babel>=2.17.0
Requires-Dist: mako>=1.3.10
Requires-Dist: pytz>=2025.2
Requires-Dist: ujson>=5.10.0
Provides-Extra: dev
Requires-Dist: loguru>=0.7.3; extra == "dev"
Requires-Dist: ruff>=0.11.12; extra == "dev"
Provides-Extra: telegrinder
Requires-Dist: telegrinder; extra == "telegrinder"
Provides-Extra: cli
Requires-Dist: typer>=0.16.0; extra == "cli"
Dynamic: license-file
